<page xmlns="http://www.mediawiki.org/xml/export-0.11/">
  <title>Classes:Meat3</title>
  <ns>0</ns>
  <id>2526</id>
  <revision>
    <id>39234</id>
    <parentid>33939</parentid>
    <timestamp>2015-04-28T20:09:50Z</timestamp>
    <contributor>
      <username>Blue Shadow</username>
      <id>2021</id>
    </contributor>
    <minor />
    <comment>/* DECORATE definition */ Updated</comment>
    <origin>39234</origin>
    <model>wikitext</model>
    <format>text/x-wiki</format>
    <text bytes="434" sha1="kkktvutuge2rknjrni4alee741gkert" xml:space="preserve">{{Actor|
| type = Gore
| name = One-legged hanging corpse
| class = Meat3
| game = Doom
| doomednum = 51
}}[[Classes]]: &lt;u&gt;Meat3&lt;/u&gt;&lt;br&gt;
&amp;ensp;&amp;rarr;[[Classes:NonsolidMeat3|NonsolidMeat3]]

{{desc}}

==== [[DECORATE]] definition ====
 ACTOR &lt;u&gt;Meat3&lt;/u&gt;
 {
   {{Property|Radius}} 16
   {{Property|Height}} 84
   +{{Flag|SOLID}}
   +{{Flag|NOGRAVITY}}
   +{{Flag|SPAWNCEILING}}
   States
   {
   Spawn:
     GOR3 A -1
     Stop
   }
 }</text>
    <sha1>kkktvutuge2rknjrni4alee741gkert</sha1>
  </revision>
</page>