<page xmlns="http://www.mediawiki.org/xml/export-0.11/">
  <title>A LoopActiveSound</title>
  <ns>0</ns>
  <id>2899</id>
  <revision>
    <id>49051</id>
    <parentid>35747</parentid>
    <timestamp>2022-03-12T11:18:09Z</timestamp>
    <contributor>
      <username>Blue Shadow</username>
      <id>2021</id>
    </contributor>
    <minor />
    <comment>A_PlaySound -&gt; A_StartSound</comment>
    <origin>49051</origin>
    <model>wikitext</model>
    <format>text/x-wiki</format>
    <text bytes="286" sha1="hev37we6xvak882uvi70ev8bf74ao27" xml:space="preserve">{{codepointer|Sound}}'''A_LoopActiveSound'''

(no parameters)

{{superseded|A_StartSound}}

==Usage==
Plays the actor's {{property|ActiveSound}}, if one is defined, and causes it to loop seamlessly.  The sound can be stopped with [[A_StopSound]].

This function doesn't work on weapons.</text>
    <sha1>hev37we6xvak882uvi70ev8bf74ao27</sha1>
  </revision>
</page>