<page xmlns="http://www.mediawiki.org/xml/export-0.11/">
  <title>Classes:AlienSpiderLight</title>
  <ns>0</ns>
  <id>3072</id>
  <revision>
    <id>40123</id>
    <parentid>36439</parentid>
    <timestamp>2015-05-22T06:46:43Z</timestamp>
    <contributor>
      <username>Blue Shadow</username>
      <id>2021</id>
    </contributor>
    <minor />
    <comment>/* DECORATE definition */ Updated</comment>
    <origin>40123</origin>
    <model>wikitext</model>
    <format>text/x-wiki</format>
    <text bytes="511" sha1="phsopxv8cwvkckwn3wh9txuafkamxbm" xml:space="preserve">{{Actor|
| type = Light source
| name = Alien spider light
| class = AlienSpiderLight
| game = Strife
| doomednum = 225
| convid = 294
}}[[Classes]]: &lt;u&gt;AlienSpiderLight&lt;/u&gt;&lt;br&gt;

An alien spider-like, pot-like gizmo which emits an ambient sound.

==== [[DECORATE]] definition ====
 ACTOR &lt;u&gt;AlienSpiderLight&lt;/u&gt;
 {
   {{Property|Radius}} 32
   {{Property|Height}} 56
   +{{Flag|SOLID}}
   {{Property|ActiveSound}} "ambient/alien1"
   States
   {
   Spawn:
     SPDL ABC 5 [[A_LoopActiveSound]]
     Loop
   }
 }</text>
    <sha1>phsopxv8cwvkckwn3wh9txuafkamxbm</sha1>
  </revision>
</page>