<page xmlns="http://www.mediawiki.org/xml/export-0.11/">
  <title>Classes:MarineChaingun</title>
  <ns>0</ns>
  <id>3880</id>
  <revision>
    <id>48878</id>
    <parentid>48466</parentid>
    <timestamp>2021-12-27T11:08:21Z</timestamp>
    <contributor>
      <username>Jekyll Grim Payne</username>
      <id>2175</id>
    </contributor>
    <comment>updated in accordance with updated ZScriptDefinitionNote template</comment>
    <origin>48878</origin>
    <model>wikitext</model>
    <format>text/x-wiki</format>
    <text bytes="671" sha1="dkzcu0iiwsej1nr5cew7h2k0gzv7voj" xml:space="preserve">{{Actor|
| type = Monster
| name = Space Marine with Chaingun
| class = MarineChaingun
| game = Doom
| doomednum = 9107
}}
[[Classes]]: [[Classes:ScriptedMarine|ScriptedMarine]]&amp;rarr;&lt;u&gt;MarineChaingun&lt;/u&gt;

A [[Classes:ScriptedMarine|scripted marine]] with a [[Classes:Chaingun|chaingun]].
==== [[ZScript]] definition ====
{{ZScriptDefinitionNote|actors/doom/scriptedmarine.zs}}
 class MarineChaingun : ScriptedMarine
 {
 	States
 	{
 	Missile:
 		Goto Super::Missile.Chaingun;
 	}
 }
==== [[DECORATE]] definition ====
{{DecorateDefinitionNote}}
 ACTOR &lt;u&gt;MarineChaingun&lt;/u&gt;: {{Class|ScriptedMarine}}
 {
   States
   {
   Missile:
     Goto Super::Missile.Chaingun
   }
 }</text>
    <sha1>dkzcu0iiwsej1nr5cew7h2k0gzv7voj</sha1>
  </revision>
</page>