<page xmlns="http://www.mediawiki.org/xml/export-0.11/">
  <title>Classes:SGShard7</title>
  <ns>0</ns>
  <id>3963</id>
  <revision>
    <id>39748</id>
    <parentid>36510</parentid>
    <timestamp>2015-05-03T22:36:07Z</timestamp>
    <contributor>
      <username>Blue Shadow</username>
      <id>2021</id>
    </contributor>
    <minor />
    <comment>/* DECORATE definition */ Updated</comment>
    <origin>39748</origin>
    <model>wikitext</model>
    <format>text/x-wiki</format>
    <text bytes="408" sha1="eip33en10gq7ixerlvsdcvu7tmwuzsp" xml:space="preserve">{{Actor|
| type = SFX
| name = Stained glass shard
| class = SGShard7
| spawnid = 60
| spawnname = T_STAINEDGLASS7 
}}[[Classes]]: [[Classes:GlassShard|GlassShard]] &amp;rarr; &lt;u&gt;SGShard7&lt;/u&gt;&lt;br&gt;

A shard of broken stained glass window.

==== [[DECORATE]] definition ====
 ACTOR &lt;u&gt;SGShard7&lt;/u&gt; : {{Class|GlassShard}}
 {
   States
   {
   Spawn:
     SGSB B 4
     Loop
   Death:
     SGSB B 30
     Stop
   }
 }</text>
    <sha1>eip33en10gq7ixerlvsdcvu7tmwuzsp</sha1>
  </revision>
</page>