<page xmlns="http://www.mediawiki.org/xml/export-0.11/">
  <title>Classes:KeySilver</title>
  <ns>0</ns>
  <id>4108</id>
  <revision>
    <id>39620</id>
    <parentid>34723</parentid>
    <timestamp>2015-05-02T20:58:28Z</timestamp>
    <contributor>
      <username>Blue Shadow</username>
      <id>2021</id>
    </contributor>
    <minor />
    <comment>/* DECORATE definition */ Updated</comment>
    <origin>39620</origin>
    <model>wikitext</model>
    <format>text/x-wiki</format>
    <text bytes="535" sha1="19hra3psvd5mc3rms5k736qam71ccpf" xml:space="preserve">{{Actor|
| type = Key
| name = Silver key
| class = KeySilver
| game = Hexen
| doomednum = 8036
| spawnid = 91
| spawnname = T_SILVERKEY 
}}
[[Classes]]: [[Classes:Inventory|Inventory]]&amp;rarr;[[Classes:Key|Key]]&amp;rarr;[[Classes:HexenKey|HexenKey]]&amp;rarr;&lt;u&gt;KeySilver&lt;/u&gt;

Silver key.

==== [[DECORATE]] definition ====
 ACTOR &lt;u&gt;KeySilver&lt;/u&gt; : {{Class|HexenKey}}
 {
   {{Property|Inventory.Icon}} KEYSLOT7
   {{Property|Inventory.PickupMessage}} "$TXT_KEY_SILVER" // "SILVER KEY"
   States
   {
   Spawn:
     KEY7 A -1
     Stop
   }
 }</text>
    <sha1>19hra3psvd5mc3rms5k736qam71ccpf</sha1>
  </revision>
</page>