<page xmlns="http://www.mediawiki.org/xml/export-0.11/">
  <title>Classes:FogPatchLarge</title>
  <ns>0</ns>
  <id>4524</id>
  <revision>
    <id>39508</id>
    <parentid>34575</parentid>
    <timestamp>2015-05-01T20:40:47Z</timestamp>
    <contributor>
      <username>Blue Shadow</username>
      <id>2021</id>
    </contributor>
    <minor />
    <comment>/* DECORATE definition */ Updated</comment>
    <origin>39508</origin>
    <model>wikitext</model>
    <format>text/x-wiki</format>
    <text bytes="524" sha1="l3u4j48cte4dopmpoddj22wtf7u7bbq" xml:space="preserve">{{Actor|
| type = SFX
| name = Large patch of fog
| class = FogPatchLarge
| game = Hexen
| doomednum = 10003
}}[[Classes]]: [[Classes:FogPatchSmall|FogPatchSmall]]&amp;rarr;[[Classes:FogPatchMedium|FogPatchMedium]]&amp;rarr;&lt;u&gt;FogPatchLarge&lt;/u&gt;&lt;br&gt;

A large patch of fog generated by a {{Class|FogSpawner}} actor.
==== [[DECORATE]] definition ====
 ACTOR &lt;u&gt;FogPatchLarge&lt;/u&gt; : {{Class|FogPatchMedium}}
 {
   States
   {
   Spawn:
     FOGL ABCDE 7 [[A_FogMove]]
     Loop
   Death:
     FOGM ABCDEF 4
     Goto Super::Death
   }
 }</text>
    <sha1>l3u4j48cte4dopmpoddj22wtf7u7bbq</sha1>
  </revision>
</page>