<page xmlns="http://www.mediawiki.org/xml/export-0.11/">
  <title>Classes:WeaponHolder</title>
  <ns>0</ns>
  <id>4706</id>
  <revision>
    <id>51614</id>
    <parentid>36563</parentid>
    <timestamp>2024-02-04T11:50:11Z</timestamp>
    <contributor>
      <username>Jekyll Grim Payne</username>
      <id>2175</id>
    </contributor>
    <origin>51614</origin>
    <model>wikitext</model>
    <format>text/x-wiki</format>
    <text bytes="555" sha1="eiezno16w9w4wzy3nipbfy76wp0x9s9" xml:space="preserve">{{Actor|
| type = Internal
| name = Weapon holder
| class = WeaponHolder
}}[[Classes]]: [[Classes:Inventory|Inventory]]&amp;rarr;&lt;u&gt;WeaponHolder&lt;/u&gt;

WeaponHolder is an internal class that is used to track information about {{class|WeaponPiece|weapon pieces}} the player has picked up until the full weapon can be assembled. It should not be inherited from in DECORATE definitions.

==== [[DECORATE]] definition ====
 ACTOR &lt;u&gt;WeaponHolder&lt;/u&gt; : {{Class|Inventory}} native
 {
   +{{Flag|NOBLOCKMAP}}
   +{{Flag|NOSECTOR}}
   +{{Flag|INVENTORY.UNDROPPABLE}}
 }</text>
    <sha1>eiezno16w9w4wzy3nipbfy76wp0x9s9</sha1>
  </revision>
</page>