<page xmlns="http://www.mediawiki.org/xml/export-0.11/">
  <title>Classes:Meat</title>
  <ns>0</ns>
  <id>4881</id>
  <revision>
    <id>35919</id>
    <parentid>19028</parentid>
    <timestamp>2013-02-15T18:32:15Z</timestamp>
    <contributor>
      <username>Deded007</username>
      <id>1392</id>
    </contributor>
    <minor />
    <comment>description</comment>
    <origin>35919</origin>
    <model>wikitext</model>
    <format>text/x-wiki</format>
    <text bytes="846" sha1="0v6lac9sg1i0d291507lzhthoaps2cy" xml:space="preserve">{{Actor|
| type = Gibs
| name = Meat
| class = Meat
| game = Strife
}}[[Classes]]: &lt;u&gt;Meat&lt;/u&gt;&lt;br&gt;
&amp;ensp;&amp;rarr;{{Class|Junk}}&lt;br&gt;

A decorative gib actor spawned by [[A_TossGib]] if called on a bleeding actor.

==== [[DECORATE]] definition ====
 ACTOR &lt;u&gt;Meat&lt;/u&gt; native
 {
   +{{flag|NOCLIP}}
   States
   {
   Spawn:
     MEAT A 700
     Stop
     MEAT B 700
     Stop
     MEAT C 700
     Stop
     MEAT D 700
     Stop
     MEAT E 700
     Stop
     MEAT F 700
     Stop
     MEAT G 700
     Stop
     MEAT H 700
     Stop
     MEAT I 700
     Stop
     MEAT J 700
     Stop
     MEAT K 700
     Stop
     MEAT L 700
     Stop
     MEAT M 700
     Stop
     MEAT N 700
     Stop
     MEAT O 700
     Stop
     MEAT P 700
     Stop
     MEAT Q 700
     Stop
     MEAT R 700
     Stop
     MEAT S 700
     Stop
     MEAT T 700
     Stop
   }
 }</text>
    <sha1>0v6lac9sg1i0d291507lzhthoaps2cy</sha1>
  </revision>
</page>