<page xmlns="http://www.mediawiki.org/xml/export-0.11/">
  <title>Weaponpiece properties</title>
  <ns>0</ns>
  <id>5100</id>
  <redirect title="WeaponPiece properties" />
  <revision>
    <id>29172</id>
    <parentid>20461</parentid>
    <timestamp>2010-11-28T11:59:38Z</timestamp>
    <contributor>
      <username>Gez</username>
      <id>1283</id>
    </contributor>
    <minor />
    <comment>+cat</comment>
    <origin>29172</origin>
    <model>wikitext</model>
    <format>text/x-wiki</format>
    <text bytes="85" sha1="qx5hz99tks8d93c44n9sjlx3alqyvuf" xml:space="preserve">#REDIRECT [[WeaponPiece properties]]
[[Category:Redirects from title capitalization]]</text>
    <sha1>qx5hz99tks8d93c44n9sjlx3alqyvuf</sha1>
  </revision>
</page>