<page xmlns="http://www.mediawiki.org/xml/export-0.11/">
  <title>MWeapWand</title>
  <ns>0</ns>
  <id>5239</id>
  <redirect title="Classes:MWeapWand" />
  <revision>
    <id>29245</id>
    <parentid>20883</parentid>
    <timestamp>2010-11-28T12:47:56Z</timestamp>
    <contributor>
      <username>Gez</username>
      <id>1283</id>
    </contributor>
    <minor />
    <comment>+cat</comment>
    <origin>29245</origin>
    <model>wikitext</model>
    <format>text/x-wiki</format>
    <text bytes="69" sha1="3dj6xski78p83b2jpt2g3la1zfqlqz7" xml:space="preserve">#redirect [[Classes:MWeapWand]]
[[Category:Redirects to actor class]]</text>
    <sha1>3dj6xski78p83b2jpt2g3la1zfqlqz7</sha1>
  </revision>
</page>