<page xmlns="http://www.mediawiki.org/xml/export-0.11/">
  <title>Supported Music Formats</title>
  <ns>0</ns>
  <id>5386</id>
  <redirect title="Music format" />
  <revision>
    <id>29292</id>
    <parentid>28603</parentid>
    <timestamp>2010-11-28T13:34:11Z</timestamp>
    <contributor>
      <username>Gez</username>
      <id>1283</id>
    </contributor>
    <minor />
    <comment>+cat</comment>
    <origin>29292</origin>
    <model>wikitext</model>
    <format>text/x-wiki</format>
    <text bytes="118" sha1="so6q9skjbnw3uubxrjkesxntnbns7sk" xml:space="preserve">#REDIRECT [[Music format]]
[[Category:Redirects from alternate names]][[Category:Redirects from title capitalization]]</text>
    <sha1>so6q9skjbnw3uubxrjkesxntnbns7sk</sha1>
  </revision>
</page>