<page xmlns="http://www.mediawiki.org/xml/export-0.11/">
  <title>A ImpXDeath1</title>
  <ns>0</ns>
  <id>5521</id>
  <revision>
    <id>23812</id>
    <timestamp>2009-08-10T17:51:24Z</timestamp>
    <contributor>
      <username>Gez</username>
      <id>1283</id>
    </contributor>
    <comment>Created page with '{{DISPLAYTITLE:A_ImpXDeath1}} '''A_ImpXDeath1'''&lt;br /&gt; (no parameters)  Clears the calling actor's SOLID flag and sets its FLOORCLIP and NOGRAVITY flags instead. Also sets the ca…'</comment>
    <origin>23812</origin>
    <model>wikitext</model>
    <format>text/x-wiki</format>
    <text bytes="535" sha1="9etssn4vokvpnyewl11j56tdc9a634a" xml:space="preserve">{{DISPLAYTITLE:A_ImpXDeath1}}
'''A_ImpXDeath1'''&lt;br /&gt;
(no parameters)

Clears the calling actor's SOLID flag and sets its FLOORCLIP and NOGRAVITY flags instead. Also sets the calling actor's &lt;tt&gt;special1&lt;/tt&gt; field to 666 to let the [[A_ImpExplode]] codepointer know to go to the XCrash state instead.

This codepointer is restricted to {{Class|HereticImp}} and derived classes.

[[Category:Decorate Heretic functions]] [[Category:Decorate Status change functions]] [[Category:Decorate Restricted functions]]{{DEFAULTSORT:ImpXDeath1}}</text>
    <sha1>9etssn4vokvpnyewl11j56tdc9a634a</sha1>
  </revision>
</page>