<page xmlns="http://www.mediawiki.org/xml/export-0.11/">
  <title>A DripBlood</title>
  <ns>0</ns>
  <id>5537</id>
  <revision>
    <id>23838</id>
    <timestamp>2009-08-11T07:19:00Z</timestamp>
    <contributor>
      <username>Gez</username>
      <id>1283</id>
    </contributor>
    <comment>Created page with '{{DISPLAYTITLE:A_DripBlood}} '''A_DripBlood'''&lt;br /&gt; (no parameters)  Spawns a {{Class|Blood}} actor within eight map units of the calling actor on both horizontal axes, gives it…'</comment>
    <origin>23838</origin>
    <model>wikitext</model>
    <format>text/x-wiki</format>
    <text bytes="503" sha1="ilcbt8nlfftydmmj2rlk60zo8xd4c7r" xml:space="preserve">{{DISPLAYTITLE:A_DripBlood}}
'''A_DripBlood'''&lt;br /&gt;
(no parameters)

Spawns a {{Class|Blood}} actor within eight map units of the calling actor on both horizontal axes, gives it a random horizontal velocity between -4 and +4 on the same axes, and sets its gravity property to 0.125.

This codepointer is restricted to {{Class|RedAxe}} and derived classes.

[[Category:Decorate Heretic functions]] [[Category:Decorate Spawn functions]] [[Category:Decorate Restricted functions]]{{DEFAULTSORT:DripBlood}}</text>
    <sha1>ilcbt8nlfftydmmj2rlk60zo8xd4c7r</sha1>
  </revision>
</page>