<page xmlns="http://www.mediawiki.org/xml/export-0.11/">
  <title>A BlueSpark</title>
  <ns>0</ns>
  <id>5538</id>
  <revision>
    <id>23839</id>
    <timestamp>2009-08-11T07:23:22Z</timestamp>
    <contributor>
      <username>Gez</username>
      <id>1283</id>
    </contributor>
    <comment>Created page with '{{DISPLAYTITLE:A_BlueSpark}} '''A_BlueSpark'''&lt;br /&gt; (no parameters)  Spawns two {{Class|Sorcerer2FXSpark}} actors and gives them different random horizontal velocities between -…'</comment>
    <origin>23839</origin>
    <model>wikitext</model>
    <format>text/x-wiki</format>
    <text bytes="469" sha1="6iy00nfoowjmjl3tyotwnuqcuyymyg5" xml:space="preserve">{{DISPLAYTITLE:A_BlueSpark}}
'''A_BlueSpark'''&lt;br /&gt;
(no parameters)

Spawns two {{Class|Sorcerer2FXSpark}} actors and gives them different random horizontal velocities between -2 and +2 on both X and Y axes, and between 1 and 2 on the Z axis.

This codepointer is restricted to {{Class|Sorcerer2FX1}} and derived classes.

[[Category:Decorate Heretic functions]] [[Category:Decorate Spawn functions]] [[Category:Decorate Restricted functions]]{{DEFAULTSORT:BlueSpark}}</text>
    <sha1>6iy00nfoowjmjl3tyotwnuqcuyymyg5</sha1>
  </revision>
</page>