<page xmlns="http://www.mediawiki.org/xml/export-0.11/">
  <title>Map arrows</title>
  <ns>0</ns>
  <id>6602</id>
  <redirect title="Map arrow" />
  <revision>
    <id>29581</id>
    <timestamp>2010-11-30T15:28:00Z</timestamp>
    <contributor>
      <username>Gez</username>
      <id>1283</id>
    </contributor>
    <comment>Redirected page to [[Map arrow]]</comment>
    <origin>29581</origin>
    <model>wikitext</model>
    <format>text/x-wiki</format>
    <text bytes="58" sha1="g6zptnhtb00ftybm7o1whnp5vzlswou" xml:space="preserve">#REDIRECT:[[Map arrow]]
[[Category:Redirects from plural]]</text>
    <sha1>g6zptnhtb00ftybm7o1whnp5vzlswou</sha1>
  </revision>
</page>