<page xmlns="http://www.mediawiki.org/xml/export-0.11/">
  <title>Alias</title>
  <ns>0</ns>
  <id>6794</id>
  <redirect title="CCMDs" />
  <revision>
    <id>30079</id>
    <timestamp>2011-01-02T13:46:17Z</timestamp>
    <contributor>
      <username>Gez</username>
      <id>1283</id>
    </contributor>
    <comment>Redirected page to [[CCMDs#Using aliases]]</comment>
    <origin>30079</origin>
    <model>wikitext</model>
    <format>text/x-wiki</format>
    <text bytes="96" sha1="ii0xd29rwh8mqdtgdvmlwt7b6d3wj9q" xml:space="preserve">#REDIRECT:[[CCMDs#Using_aliases]]
[[Category:Glossary]][[Category:Redirects for categorization]]</text>
    <sha1>ii0xd29rwh8mqdtgdvmlwt7b6d3wj9q</sha1>
  </revision>
</page>