<page xmlns="http://www.mediawiki.org/xml/export-0.11/">
  <title>Thing SpawnNoFog</title>
  <ns>0</ns>
  <id>707</id>
  <revision>
    <id>40824</id>
    <parentid>36662</parentid>
    <timestamp>2016-02-06T05:34:40Z</timestamp>
    <contributor>
      <username>Jpalomo</username>
      <id>1715</id>
    </contributor>
    <minor />
    <origin>40824</origin>
    <model>wikitext</model>
    <format>text/x-wiki</format>
    <text bytes="1422" sha1="3t59q38ufc12syla2bserjqb0tvxc96" xml:space="preserve">{{DISPLAYTITLE:Thing_SpawnNoFog}}
{{Special|137|tid, type, angle, newtid|Thing|SpawnNoFog}}

* ''tid'': [[Thing ID]] of the map spot to spawn the thing at 
* ''type'': [[Spawn number|Type]] of thing to spawn 
* ''angle'': [[Definitions#Byte_Angles|Byte angle]] for the thing to face
* ''newtid'': TID to give spawned thing

Spawns a thing without the teleporter fog. Note that this special requires the actor being spawned to have a [[Spawn number|SpawnID]]. To spawn an actor without one, use the [[SpawnSpot]] function instead.

== Usage ==

* ''tid'' is a number that makes a thing unique, the default is zero, and therefore, a TID is usually set to something else, like 1. In Doom Builder, you have to right-click on a thing, select the “Effects” tab and change the Thing Tag to something besides 0.

* The ''type'' is actually from the list of [[spawn numbers]]. You can either use the number or the defined name (T_SOMETHING) for clarity.

: When using this special on a [[linedef]] or a [[thing]] in [[UDMF]], you can use the {{c|arg1str}} property to define a class name instead of the {{c|arg1}} property to define a spawn number.

* ''angle'' is a number between 0&amp;ndash;255, representing a [[Definitions#Byte_Angles|byte angle]].

* ''newtid'' is just a way to make the spawned thing unique if you need to refer to it later. It is just a number.

==Examples==
{{noexamples}}

==External links==
* {{oldref}}</text>
    <sha1>3t59q38ufc12syla2bserjqb0tvxc96</sha1>
  </revision>
</page>