<page xmlns="http://www.mediawiki.org/xml/export-0.11/">
  <title>ClearCounters</title>
  <ns>0</ns>
  <id>9210</id>
  <revision>
    <id>46033</id>
    <parentid>45647</parentid>
    <timestamp>2018-04-25T22:35:51Z</timestamp>
    <contributor>
      <username>LordMisfit</username>
      <id>1752</id>
    </contributor>
    <minor />
    <comment>Giving a bit more clarity after some confusion experienced on my part with this. &gt;.&gt;</comment>
    <origin>46033</origin>
    <model>wikitext</model>
    <format>text/x-wiki</format>
    <text bytes="480" sha1="ibvgsyv2mnmlpe54jnq029tgpnv60a5" xml:space="preserve">void '''ClearCounters''' ()

==Usage==
Excludes the calling actor from being counted towards the map's kills, items and secrets. For the kills, the actor needs to be non-{{Flag|FRIENDLY|friendly}} and alive to not be counted successfully, so if this is being done for changing an enemy to a friendly to remove them from the monster count, for example, it must be placed ''before'' the friendly flag is set.

==Examples==
{{noexamples}}


[[Category:DECORATE]]
[[Category:ZScript]]</text>
    <sha1>ibvgsyv2mnmlpe54jnq029tgpnv60a5</sha1>
  </revision>
</page>