<page xmlns="http://www.mediawiki.org/xml/export-0.11/">
  <title>RemoveFromHash</title>
  <ns>0</ns>
  <id>9474</id>
  <revision>
    <id>47996</id>
    <timestamp>2020-10-09T22:00:28Z</timestamp>
    <contributor>
      <username>Boondorl</username>
      <id>2606</id>
    </contributor>
    <comment>Created page with "{{ZScriptNote}} __NOTOC__  void '''RemoveFromHash'''()  == Usage == Sets the Actor's thing id to 0 and removes it from the internal list that keeps track of things with ids. S..."</comment>
    <origin>47996</origin>
    <model>wikitext</model>
    <format>text/x-wiki</format>
    <text bytes="343" sha1="73xc6q79g41racjcgzswo5v3ixwwfcs" xml:space="preserve">{{ZScriptNote}}
__NOTOC__

void '''RemoveFromHash'''()

== Usage ==
Sets the Actor's thing id to 0 and removes it from the internal list that keeps track of things with ids. Should be used when completely removing a thing's id is wanted. Also called when using a thing id changing function.

== Examples ==
{{noexamples}}

[[Category:ZScript]]</text>
    <sha1>73xc6q79g41racjcgzswo5v3ixwwfcs</sha1>
  </revision>
</page>