<page xmlns="http://www.mediawiki.org/xml/export-0.11/">
  <title>MenuTime</title>
  <ns>0</ns>
  <id>9657</id>
  <revision>
    <id>49882</id>
    <timestamp>2022-11-23T05:18:31Z</timestamp>
    <contributor>
      <username>Boondorl</username>
      <id>2606</id>
    </contributor>
    <comment>Created page with "{{ZScriptNote}}  '''[[Classes:Menu|Menu]]'''  native static int '''MenuTime'''()  == Usage == Gets the total number of tics where any menu has been open. This does not track m..."</comment>
    <origin>49882</origin>
    <model>wikitext</model>
    <format>text/x-wiki</format>
    <text bytes="335" sha1="2priorrrnfx07skduy488ap2ozvnt0a" xml:space="preserve">{{ZScriptNote}}

'''[[Classes:Menu|Menu]]'''

native static int '''MenuTime'''()

== Usage ==
Gets the total number of tics where any menu has been open. This does not track menus individually. 35 tics is 1 second.

=== Return Value ===
Returns the number of tics.

== Examples ==
{{noexamples}}

[[Category:ZScript]]
[[Category:Menu]]</text>
    <sha1>2priorrrnfx07skduy488ap2ozvnt0a</sha1>
  </revision>
</page>